brainreg/__init__.py
brainreg/core/__init__.py
brainreg/core/cli.py
brainreg/core/main.py
brainreg/core/paths.py
brainreg/core/backend/__init__.py
brainreg/core/backend/niftyreg/__init__.py
brainreg/core/backend/niftyreg/niftyreg_binaries.py
brainreg/core/backend/niftyreg/parameters.py
brainreg/core/backend/niftyreg/parser.py
brainreg/core/backend/niftyreg/paths.py
brainreg/core/backend/niftyreg/registration.py
brainreg/core/backend/niftyreg/run.py
brainreg/core/backend/niftyreg/utils.py
brainreg/core/bin/nifty_reg/LICENSE.txt
brainreg/core/bin/nifty_reg/niftyreg_version.txt
brainreg/core/bin/nifty_reg/linux_x64/reg_aladin
brainreg/core/bin/nifty_reg/linux_x64/reg_average
brainreg/core/bin/nifty_reg/linux_x64/reg_f3d
brainreg/core/bin/nifty_reg/linux_x64/reg_jacobian
brainreg/core/bin/nifty_reg/linux_x64/reg_measure
brainreg/core/bin/nifty_reg/linux_x64/reg_resample
brainreg/core/bin/nifty_reg/linux_x64/reg_tools
brainreg/core/bin/nifty_reg/linux_x64/reg_transform
brainreg/core/bin/nifty_reg/osX/reg_aladin
brainreg/core/bin/nifty_reg/osX/reg_average
brainreg/core/bin/nifty_reg/osX/reg_f3d
brainreg/core/bin/nifty_reg/osX/reg_jacobian
brainreg/core/bin/nifty_reg/osX/reg_measure
brainreg/core/bin/nifty_reg/osX/reg_resample
brainreg/core/bin/nifty_reg/osX/reg_tools
brainreg/core/bin/nifty_reg/osX/reg_transform
brainreg/core/bin/nifty_reg/win64/reg_aladin.exe
brainreg/core/bin/nifty_reg/win64/reg_average.exe
brainreg/core/bin/nifty_reg/win64/reg_f3d.exe
brainreg/core/bin/nifty_reg/win64/reg_jacobian.exe
brainreg/core/bin/nifty_reg/win64/reg_measure.exe
brainreg/core/bin/nifty_reg/win64/reg_resample.exe
brainreg/core/bin/nifty_reg/win64/reg_tools.exe
brainreg/core/bin/nifty_reg/win64/reg_transform.exe
brainreg/core/bin/nifty_reg/win64/vcruntime140_1.dll
brainreg/core/utils/__init__.py
brainreg/core/utils/boundaries.py
brainreg/core/utils/misc.py
brainreg/core/utils/preprocess.py
brainreg/core/utils/volume.py
brainreg/napari/__init__.py
brainreg/napari/napari.yaml
brainreg-1.0.14.dist-info/licenses/LICENSE
brainreg-1.0.14.dist-info/METADATA
brainreg-1.0.14.dist-info/WHEEL
brainreg-1.0.14.dist-info/entry_points.txt
brainreg-1.0.14.dist-info/top_level.txt
brainreg-1.0.14.dist-info/RECORD
