Metadata-Version: 2.4
Name: brainreg
Version: 1.0.14
Summary: Automated multi-atlas whole-brain microscopy registration
Author-email: "Adam Tyson, Charly Rousseau, Stephen Lenzi" <code@adamltyson.com>
License: BSD 3-Clause License
Project-URL: Homepage, https://brainglobe.info
Project-URL: Bug Tracker, https://github.com/brainglobe/brainreg/issues
Project-URL: Documentation, https://docs.brainglobe.info/brainreg
Project-URL: Source Code, https://github.com/brainglobe/brainreg
Project-URL: User support, https://forum.image.sc/tag/brainglobe
Project-URL: Twitter, https://twitter.com/brain_globe
Classifier: Development Status :: 3 - Alpha
Classifier: Intended Audience :: Developers
Classifier: Intended Audience :: Science/Research
Classifier: Operating System :: OS Independent
Classifier: Programming Language :: Python
Classifier: Programming Language :: Python :: 3.11
Classifier: Programming Language :: Python :: 3.12
Classifier: Programming Language :: Python :: 3.13
Classifier: Framework :: napari
Requires-Python: >=3.11
License-File: LICENSE
Requires-Dist: brainglobe-atlasapi>=2.0.1
Requires-Dist: brainglobe-space>=1.0.0
Requires-Dist: brainglobe-utils>=0.5.0
Requires-Dist: fancylog
Requires-Dist: numpy
Requires-Dist: scikit-image>=0.24.0
Provides-Extra: napari
Requires-Dist: brainglobe-napari-io>=0.3.2; extra == "napari"
Requires-Dist: brainglobe-segmentation>=1.0.0; extra == "napari"
Requires-Dist: magicgui; extra == "napari"
Requires-Dist: napari-plugin-engine>=0.1.4; extra == "napari"
Requires-Dist: napari[pyqt5]>=0.6.1; extra == "napari"
Requires-Dist: pooch>1; extra == "napari"
Requires-Dist: qtpy; extra == "napari"
Provides-Extra: dev
Requires-Dist: black; extra == "dev"
Requires-Dist: check-manifest; extra == "dev"
Requires-Dist: gitpython; extra == "dev"
Requires-Dist: napari[pyqt5]>=0.6.1; extra == "dev"
Requires-Dist: pre-commit; extra == "dev"
Requires-Dist: pytest-cov; extra == "dev"
Requires-Dist: pytest-qt; extra == "dev"
Requires-Dist: pytest-mock; extra == "dev"
Requires-Dist: pytest; extra == "dev"
Requires-Dist: setuptools_scm; extra == "dev"
Requires-Dist: tox; extra == "dev"
Dynamic: license-file
